{
  "Ads": [
    {
      "select_main_ads": "ADMOB",
      "select_backup_ads":"APPLOVIN-M",
      "main_ads_banner": "ca-app-pub-9433218134790007/9054850401x",
      "main_ads_intertitial":"ca-app-pub-9433218134790007/5753899649",
      "main_native_ads_Admob_or_applovin":"ca-app-pub-9433218134790007/7741768737",
      "backup_native_ads_Admob_or_applovin":"4c29ae5af57524c0x",
      "backup_ads_banner":"f200f47fd52553cb",
      "backup_ads_intertitial":"2e54be518aaa80c3x",
      "interval_intertitial": 3,
      "initialize_sdk":"1234567",
      "initialize_sdk_backup_ads":"1234567",
      "high_paying_keyword_1": "",
      "high_paying_keyword_2": "",
      "high_paying_keyword_3": "",
      "high_paying_keyword_4": "",
      "high_paying_keyword_5": "",
      "status_app": "0",
      "link_redirect": "https://",
      "matikan_iklan":"0"
    }
  ],
  "More":
  [
    
  ],

  "Categories": [
    
  ],

  "Data":
  [
    
  ]
}
